[
  {
    "id": 1,
    "name": {
      "en": "Borjgali",
      "ka": "ბორჯღალა"
    },
    "category": [
      "Celestial",
      "Geometric"
    ],
    "preview": {
      "en": "The astral symbol of the Sun, now transformed into a traditional Caucasian ornament",
      "ka": "მზის ასტრალური სიმბოლო, ტრადიციულ ქართულ-კავკასიურ ორნამენტად გარდასახული"
    },
    "description": {
      "en": "The astral symbol of the Sun, now transformed to a traditional Caucasian ornament",
      "ka": "მზის ასტრალური სიმბოლო, ტრადიციულ ქართულ-კავკასიურ ორნამენტად გარდასახული"
    },
    "region": {
      "en": "Pan-Caucasian",
      "ka": "პანკავკასიური"
    },
    "image": "images/photo1.jpg",
    "map": "assets/CaucasusMap.svg",
    "pinCoords": {
      "x": 45,
      "y": 35
    }
  },
  {
    "id": 2,
    "name": {
      "en": "Grapevine Motif",
      "ka": "ვაზის ორნამენტი"
    },
    "category": [
      "Nature",
      "Christian"
    ],
    "preview": {
      "en": "A sacred object of worship, rooted deep in the history of Georgia",
      "ka": "უძველესი ქართული, საკრალური თაყვანისცემის ობიექტი"
    },
    "description": {
      "en": "The grapevine is deeply sacred in Georgia, the birthplace of wine. The stylized grapevine motif once belonging to the cult of the grapevine transphormed into a christan symbol, representing the blood of christ and the eucharist.",
      "ka": "ღვინის სამშობლოში ვაზის სიმბოლო დღემდე უძლიერესია. ოდესღაც ვაზის კულტის აღმნიშვნელი ნიშანი, ქრისტეს სისხლისა და ზიარების სიმბოლოდ იქცა."
    },
    "region": {
      "en": "Kakheti",
      "ka": "კახეთი"
    },
    "image": "images/photo2.jpg",
    "map": "assets/CaucasusMap.svg",
    "pinCoords": {
      "x": 40,
      "y": 55
    }
  },
  {
    "id": 3,
    "name": {
      "en": "Stag and Deer",
      "ka": "ირემი"
    },
    "category": [
      "Animalistic",
      "Christian"  
    ],
    "preview": {
      "en": "A divine animal, thought to connect the realms with it's horns",
      "ka": "მოიაზრებოდა, რომ ეს საკრალური ცხოველი სკნელებს თავისი რქებით აკავშირებდა"
    },
    "description": {
      "en": "Found in the mountainous Pshavi region, these intricate geometric crosses combine Christian iconography with ancient pagan solar symbols.",
      "ka": "აღმოჩენილია ფშავის მაღალმთიანეთში. ეს გეომეტრიული ჯვრები აერთიანებს ქრისტიანულ იკონოგრაფიასა და უძველეს წარმართულ მზის სიმბოლოებს."
    },
    "region": {
      "en": "N/A",
      "ka": "N/A"
    },
    "image": "images/photo3.jpg",
    "map": "assets/CaucasusMap.svg",
    "pinCoords": {
      "x": 40,
      "y": 55
    }
  }
]
